email3/__init__.py
email3/email3.py
email3-0.0.3.dist-info/LICENSE.txt
email3-0.0.3.dist-info/METADATA
email3-0.0.3.dist-info/WHEEL
email3-0.0.3.dist-info/top_level.txt
email3-0.0.3.dist-info/RECORD
