Metadata-Version: 2.1
Name: email3
Version: 0.0.3
Summary: simple email sender
Home-page: https://gitee.com/gan_jian_wen_main/demo-gan
Author: 甘建文
Author-email: 1727949032@qq.com
License: UNKNOWN
Platform: UNKNOWN
Classifier: Programming Language :: Python :: 3
Classifier: License :: OSI Approved :: MIT License
Classifier: Operating System :: OS Independent
Requires-Python: >=3.6
